{
  "aiTs": "7/17/2026, 7:16:06 AM (Gemini)",
  "aiEpoch": 1784286966236,
  "v": 10,
  "src": "Gemini",
  "modes": {
    "conservative": {
      "moves": [
        {
          "sym": "SPY",
          "action": "Trim",
          "targetPct": 20,
          "note": "Reduce concentration, meet mandate"
        },
        {
          "sym": "SOXL",
          "action": "Sell",
          "targetPct": 0,
          "note": "Eliminate leveraged ETF"
        },
        {
          "sym": "SPAL",
          "action": "Sell",
          "targetPct": 0,
          "note": "Eliminate leveraged ETF"
        },
        {
          "sym": "QQQI",
          "action": "Add",
          "targetPct": 25,
          "note": "Increase income, broad exposure"
        },
        {
          "sym": "QQQ",
          "action": "Trim",
          "targetPct": 15,
          "note": "Reduce broad index, meet mandate"
        },
        {
          "sym": "SMH",
          "action": "Trim",
          "targetPct": 5,
          "note": "Reduce weak sector exposure"
        }
      ],
      "plan": [
        "We'll trim SPY to reduce concentration and meet the single-name mandate.",
        "All leveraged ETFs, SOXL and SPAL, will be sold to zero to preserve capital.",
        "QQQI will be increased to enhance income and broad market exposure.",
        "QQQ and SMH will be trimmed to reduce overall broad index and weak sector exposure.",
        "This plan aims for capital preservation by reducing risk and leverage significantly.",
        "A substantial cash buffer will be maintained for stability and future opportunities."
      ],
      "read": "This conservative plan targets approximately 1.5% monthly growth, prioritizing capital preservation. It significantly reduces leverage and concentration, aiming for lower drawdown. However, it will likely underperform in strong bull markets."
    },
    "balanced": {
      "moves": [
        {
          "sym": "SPY",
          "action": "Trim",
          "targetPct": 25,
          "note": "Reduce concentration, meet mandate"
        },
        {
          "sym": "SOXL",
          "action": "Sell",
          "targetPct": 0,
          "note": "Exit below stop, reduce leverage"
        },
        {
          "sym": "SPAL",
          "action": "Sell",
          "targetPct": 0,
          "note": "Exit below stop, reduce leverage"
        },
        {
          "sym": "QQQI",
          "action": "Trim",
          "targetPct": 15,
          "note": "Reduce weak performer, balance"
        },
        {
          "sym": "QQQ",
          "action": "Trim",
          "targetPct": 10,
          "note": "Reduce weak performer, balance"
        },
        {
          "sym": "SMH",
          "action": "Trim",
          "targetPct": 5,
          "note": "Reduce weak performer, balance"
        },
        {
          "sym": "ZS",
          "action": "Buy",
          "targetPct": 8,
          "note": "Add strong risk/reward setup"
        }
      ],
      "plan": [
        "SPY will be trimmed to meet the single-name concentration mandate.",
        "All leveraged ETFs, SOXL and SPAL, will be sold to reduce overall leverage.",
        "QQQI, QQQ, and SMH will be trimmed to reduce exposure to weaker performers.",
        "ZS will be bought as a new position, leveraging its strong scanner setup.",
        "This plan balances growth with risk management, maintaining a moderate cash buffer.",
        "The goal is to reduce overall portfolio leverage and concentration."
      ],
      "read": "This balanced plan targets approximately 2.5% monthly growth, focusing on risk-first growth. It reduces leverage and concentration while adding quality setups. Expect moderate drawdowns, but it may not capture extreme upside."
    },
    "aggressive": {
      "moves": [
        {
          "sym": "SPY",
          "action": "Trim",
          "targetPct": 25,
          "note": "Meet concentration mandate"
        },
        {
          "sym": "SOXL",
          "action": "Sell",
          "targetPct": 0,
          "note": "Exit below stop, reallocate"
        },
        {
          "sym": "SPAL",
          "action": "Sell",
          "targetPct": 0,
          "note": "Exit below stop, reallocate"
        },
        {
          "sym": "QQQI",
          "action": "Trim",
          "targetPct": 10,
          "note": "Reduce weak performer, reallocate"
        },
        {
          "sym": "QQQ",
          "action": "Trim",
          "targetPct": 10,
          "note": "Reduce weak performer, reallocate"
        },
        {
          "sym": "SMH",
          "action": "Trim",
          "targetPct": 5,
          "note": "Reduce weak performer, reallocate"
        },
        {
          "sym": "ZS",
          "action": "Buy",
          "targetPct": 10,
          "note": "Strongest risk/reward setup"
        },
        {
          "sym": "NVDA",
          "action": "Buy",
          "targetPct": 10,
          "note": "High-conviction tech play"
        }
      ],
      "plan": [
        "SPY will be trimmed to meet the single-name concentration mandate.",
        "SOXL and SPAL will be sold to exit positions below their stops.",
        "QQQI, QQQ, and SMH will be trimmed to reallocate from weaker performers.",
        "ZS and NVDA will be bought, leaning into high-scoring growth setups.",
        "This aggressive plan focuses on stretching growth with concentrated bets.",
        "Leverage will be managed within limits, with strict stop discipline."
      ],
      "read": "This aggressive plan targets approximately 4% monthly growth, aiming for stretched growth. It involves higher concentration and leverage, leading to potentially larger drawdowns. Be aware that leveraged ETFs decay daily, magnifying both gains and losses."
    },
    "income": {
      "moves": [
        {
          "sym": "SPY",
          "action": "Trim",
          "targetPct": 20,
          "note": "Reduce concentration, rebalance"
        },
        {
          "sym": "SOXL",
          "action": "Sell",
          "targetPct": 0,
          "note": "Eliminate leveraged ETF"
        },
        {
          "sym": "SPAL",
          "action": "Sell",
          "targetPct": 0,
          "note": "Eliminate leveraged ETF"
        },
        {
          "sym": "QQQI",
          "action": "Add",
          "targetPct": 30,
          "note": "Increase income, broad exposure"
        },
        {
          "sym": "QQQ",
          "action": "Trim",
          "targetPct": 10,
          "note": "Reduce growth exposure"
        },
        {
          "sym": "CRWD",
          "action": "Trim",
          "targetPct": 5,
          "note": "Reduce high-beta single name"
        },
        {
          "sym": "SMH",
          "action": "Trim",
          "targetPct": 5,
          "note": "Reduce weak sector exposure"
        }
      ],
      "plan": [
        "SPY will be trimmed to reduce concentration and rebalance the portfolio.",
        "All leveraged ETFs, SOXL and SPAL, will be sold to eliminate high-beta exposure.",
        "QQQI will be significantly increased to prioritize steady monthly distributions.",
        "QQQ, CRWD, and SMH will be trimmed to reduce growth and high-beta exposure.",
        "This plan focuses on generating reliable income with a low drawdown profile.",
        "A cash buffer will be maintained for stability and to smooth out distributions."
      ],
      "read": "This income plan targets approximately 1% monthly yield, prioritizing steady distributions. It significantly reduces leverage and high-beta names for lower drawdown. While aiming for reliable income, distributions are variable, and NAV can still fall in selloffs."
    }
  }
}