{
  "aiTs": "7/20/2026, 5:01:18 AM (Gemini)",
  "aiEpoch": 1784538078368,
  "v": 10,
  "src": "Gemini",
  "modes": {
    "conservative": {
      "moves": [
        {
          "sym": "SOXL",
          "action": "Sell",
          "targetPct": 0,
          "note": "Cut leveraged ETFs to zero"
        },
        {
          "sym": "SPAL",
          "action": "Sell",
          "targetPct": 0,
          "note": "Cut leveraged ETFs to zero"
        },
        {
          "sym": "QQQI",
          "action": "Add",
          "targetPct": 15,
          "note": "Increase income focus"
        },
        {
          "sym": "SPY",
          "action": "Trim",
          "targetPct": 20,
          "note": "Reduce concentration, add cash"
        },
        {
          "sym": "QQQ",
          "action": "Trim",
          "targetPct": 10,
          "note": "Reduce broad index, add cash"
        },
        {
          "sym": "XOM",
          "action": "Buy",
          "targetPct": 10,
          "note": "Add strong energy name"
        },
        {
          "sym": "COP",
          "action": "Buy",
          "targetPct": 10,
          "note": "Add strong energy name"
        }
      ],
      "plan": [
        "Sell all leveraged ETFs (SOXL, SPAL) to eliminate high risk.",
        "Increase allocation to income ETF QQQI for stability.",
        "Trim broad index ETFs (SPY, QQQ) to reduce concentration and build cash.",
        "Buy XOM and COP, strong energy names, for diversification.",
        "This plan prioritizes capital preservation with a significant cash buffer.",
        "Expect lower volatility and a modest target return."
      ],
      "read": "This plan aims for capital preservation with a target of ~1.5% monthly return. It significantly reduces leverage and concentrates on income and stable assets, leading to lower expected drawdowns."
    },
    "balanced": {
      "moves": [
        {
          "sym": "SOXL",
          "action": "Trim",
          "targetPct": 2,
          "note": "Reduce leveraged ETF exposure"
        },
        {
          "sym": "SPAL",
          "action": "Sell",
          "targetPct": 0,
          "note": "Eliminate highly leveraged ETF"
        },
        {
          "sym": "SPY",
          "action": "Trim",
          "targetPct": 25,
          "note": "Reduce concentration, add cash"
        },
        {
          "sym": "QQQ",
          "action": "Trim",
          "targetPct": 15,
          "note": "Reduce broad index, add cash"
        },
        {
          "sym": "CRWD",
          "action": "Add",
          "targetPct": 15,
          "note": "Increase exposure to strong tech"
        },
        {
          "sym": "AMD",
          "action": "Buy",
          "targetPct": 10,
          "note": "Add strong semiconductor name"
        },
        {
          "sym": "META",
          "action": "Buy",
          "targetPct": 10,
          "note": "Add strong software name"
        }
      ],
      "plan": [
        "Trim leveraged ETF SOXL and sell SPAL to reduce overall leverage.",
        "Reduce concentration in SPY and QQQ to build a cash buffer.",
        "Increase position in strong performer CRWD.",
        "Add new positions in promising tech names AMD and META.",
        "This approach balances growth with risk reduction.",
        "Expect moderate growth with controlled drawdowns."
      ],
      "read": "This balanced plan targets ~2.5% monthly return by reducing leverage and concentration while adding quality growth names. It aims for risk-first growth, accepting moderate drawdowns for higher potential gains."
    },
    "aggressive": {
      "moves": [
        {
          "sym": "SOXL",
          "action": "Add",
          "targetPct": 8,
          "note": "Increase leveraged ETF exposure"
        },
        {
          "sym": "SPY",
          "action": "Trim",
          "targetPct": 20,
          "note": "Reduce concentration slightly"
        },
        {
          "sym": "QQQ",
          "action": "Trim",
          "targetPct": 10,
          "note": "Reduce broad index, add cash"
        },
        {
          "sym": "CRWD",
          "action": "Add",
          "targetPct": 20,
          "note": "Increase exposure to strong tech"
        },
        {
          "sym": "SMH",
          "action": "Sell",
          "targetPct": 0,
          "note": "Exit weak semiconductor ETF"
        },
        {
          "sym": "AMD",
          "action": "Buy",
          "targetPct": 15,
          "note": "Add strong semiconductor name"
        },
        {
          "sym": "META",
          "action": "Buy",
          "targetPct": 15,
          "note": "Add strong software name"
        }
      ],
      "plan": [
        "Increase position in leveraged SOXL, accepting higher risk for amplified gains.",
        "Trim SPY and QQQ to free up capital for higher conviction plays.",
        "Significantly increase allocation to strong performer CRWD.",
        "Sell the weak SMH ETF.",
        "Add high-potential tech names AMD and META.",
        "This plan aggressively pursues growth with concentrated high-conviction bets and leverage."
      ],
      "read": "This aggressive plan targets ~4% monthly return by leaning into leverage and concentrated high-scoring setups. It accepts significantly higher potential drawdowns due to increased leverage and concentrated positions, requiring strict stop discipline."
    },
    "income": {
      "moves": [
        {
          "sym": "SOXL",
          "action": "Sell",
          "targetPct": 0,
          "note": "Cut all leveraged ETFs"
        },
        {
          "sym": "SPAL",
          "action": "Sell",
          "targetPct": 0,
          "note": "Cut all leveraged ETFs"
        },
        {
          "sym": "CRWD",
          "action": "Sell",
          "targetPct": 0,
          "note": "Cut high-beta single names"
        },
        {
          "sym": "QQQ",
          "action": "Sell",
          "targetPct": 0,
          "note": "Cut growth index"
        },
        {
          "sym": "QQQI",
          "action": "Add",
          "targetPct": 40,
          "note": "Maximize income focus"
        },
        {
          "sym": "SPY",
          "action": "Add",
          "targetPct": 30,
          "note": "Add broad index for yield"
        },
        {
          "sym": "XOM",
          "action": "Buy",
          "targetPct": 15,
          "note": "Add stable dividend payer"
        },
        {
          "sym": "COP",
          "action": "Buy",
          "targetPct": 15,
          "note": "Add stable dividend payer"
        }
      ],
      "plan": [
        "Sell all leveraged ETFs (SOXL, SPAL) and high-beta tech (CRWD, QQQ).",
        "Maximize allocation to income-focused QQQI for steady distributions.",
        "Add broad index SPY for potential yield and stability.",
        "Buy energy stocks XOM and COP for their dividend income.",
        "This plan prioritizes consistent monthly income and capital preservation.",
        "Expect low drawdowns and reliable, though variable, income distributions."
      ],
      "read": "This income plan targets ~1% monthly return by focusing on yield-generating assets and reducing volatility. It prioritizes stable monthly distributions over growth, with low expected drawdowns but variable income."
    }
  }
}