{
  "aiTs": "7/2/2026, 12:31:21 PM (Gemini)",
  "aiEpoch": 1783009881411,
  "v": 7,
  "src": "Gemini",
  "modes": {
    "conservative": {
      "moves": [
        {
          "sym": "CRWD",
          "action": "Sell",
          "targetPct": 0,
          "note": "Exit losing, flagged position."
        },
        {
          "sym": "SOXL",
          "action": "Sell",
          "targetPct": 0,
          "note": "Exit all leveraged ETFs."
        },
        {
          "sym": "SPAL",
          "action": "Sell",
          "targetPct": 0,
          "note": "Exit all leveraged ETFs."
        },
        {
          "sym": "QQQI",
          "action": "Add",
          "targetPct": 25,
          "note": "Increase income, flagged trim."
        },
        {
          "sym": "SPY",
          "action": "Add",
          "targetPct": 40,
          "note": "Increase broad index, stability."
        },
        {
          "sym": "PANW",
          "action": "Buy",
          "targetPct": 5,
          "note": "Add high R/R quality tech."
        }
      ],
      "plan": [
        "Sell CRWD and all leveraged ETFs (SOXL, SPAL) to eliminate high-risk positions and meet capital preservation goals.",
        "Increase SPY and QQQI to strengthen broad market exposure and income generation.",
        "Add a small allocation to PANW for quality tech exposure with a strong risk/reward.",
        "Maintain a significant cash buffer by reducing overall exposure, ensuring tight stops on all positions.",
        "This plan aims for capital preservation and steady, low-drawdown performance.",
        "Keep any single name <=20% and any sector <=45%."
      ],
      "read": "This conservative approach targets around 1.5% per month, prioritizing capital preservation and stability. It significantly reduces risk by eliminating leveraged products and concentrating on broad market and income-generating assets. Expect lower volatility, but also limited upside potential."
    },
    "balanced": {
      "moves": [
        {
          "sym": "CRWD",
          "action": "Sell",
          "targetPct": 0,
          "note": "Exit losing, flagged position."
        },
        {
          "sym": "SOXL",
          "action": "Trim",
          "targetPct": 2,
          "note": "Reduce leveraged ETF to small."
        },
        {
          "sym": "SPAL",
          "action": "Trim",
          "targetPct": 1,
          "note": "Reduce leveraged ETF to small."
        },
        {
          "sym": "QQQI",
          "action": "Add",
          "targetPct": 25,
          "note": "Increase income, flagged trim."
        },
        {
          "sym": "PANW",
          "action": "Buy",
          "targetPct": 7,
          "note": "Add high R/R quality tech."
        },
        {
          "sym": "XLK",
          "action": "Buy",
          "targetPct": 5,
          "note": "Add quality tech sector."
        }
      ],
      "plan": [
        "Sell CRWD to remove a significant underperformer flagged by the scanner.",
        "Trim SOXL and SPAL to small allocations, reducing overall leverage but retaining some exposure.",
        "Increase QQQI for stable income and to address the scanner's trim flag.",
        "Add PANW and XLK for quality tech exposure with good risk/reward profiles.",
        "Maintain a cash buffer of approximately 10% to manage risk and allow for opportunistic buys.",
        "Keep total adds <= total trims + buffer for controlled growth."
      ],
      "read": "This balanced strategy aims for approximately 2.5% per month, focusing on risk-first growth. It reduces concentration and leverage while blending broad market exposure with quality tech. Expect moderate volatility and growth potential, with a focus on managing drawdowns."
    },
    "aggressive": {
      "moves": [
        {
          "sym": "CRWD",
          "action": "Sell",
          "targetPct": 0,
          "note": "Exit losing, flagged position."
        },
        {
          "sym": "QQQI",
          "action": "Trim",
          "targetPct": 10,
          "note": "Reduce income for growth focus."
        },
        {
          "sym": "SOXL",
          "action": "Add",
          "targetPct": 10,
          "note": "Increase leveraged semi exposure."
        },
        {
          "sym": "TQQQ",
          "action": "Buy",
          "targetPct": 8,
          "note": "Add leveraged tech index."
        },
        {
          "sym": "PANW",
          "action": "Buy",
          "targetPct": 10,
          "note": "Add highest R/R quality tech."
        },
        {
          "sym": "ALAB",
          "action": "Buy",
          "targetPct": 7,
          "note": "Add high R/R tech."
        }
      ],
      "plan": [
        "Sell CRWD to remove a significant underperformer and free up capital.",
        "Trim QQQI to reduce income focus and reallocate to higher growth potential.",
        "Increase SOXL and add TQQQ to lean into leveraged tech and semiconductor exposure.",
        "Initiate positions in PANW and ALAB, focusing on the highest-scoring scanner setups for aggressive growth.",
        "Maintain a smaller cash buffer (~5%) to maximize deployed capital.",
        "Utilize wider but strict stops to manage increased risk from leverage and concentration."
      ],
      "read": "This aggressive strategy targets around 4% per month, aiming for stretched growth. It involves significant use of leveraged ETFs and concentration in high-scoring setups, which can lead to larger drawdowns and daily decay. This approach requires strict stop discipline and acknowledges the potential for rapid losses alongside higher upside."
    },
    "income": {
      "moves": [
        {
          "sym": "CRWD",
          "action": "Sell",
          "targetPct": 0,
          "note": "Exit high-beta, losing position."
        },
        {
          "sym": "SOXL",
          "action": "Sell",
          "targetPct": 0,
          "note": "Exit all leveraged ETFs."
        },
        {
          "sym": "SPAL",
          "action": "Sell",
          "targetPct": 0,
          "note": "Exit all leveraged ETFs."
        },
        {
          "sym": "QQQI",
          "action": "Add",
          "targetPct": 40,
          "note": "Maximize income, flagged trim."
        },
        {
          "sym": "SPY",
          "action": "Add",
          "targetPct": 40,
          "note": "Increase broad index for stability."
        }
      ],
      "plan": [
        "Sell CRWD, SOXL, and SPAL to eliminate high-beta and leveraged positions, prioritizing low drawdown.",
        "Significantly increase QQQI to maximize income generation and address the scanner's trim flag.",
        "Increase SPY to provide broad market exposure and stability, balancing income with underlying asset health.",
        "Maintain a cash buffer to further reduce risk and provide liquidity for monthly distributions.",
        "This plan focuses on steady monthly distributions and capital preservation over growth.",
        "Prioritize low drawdown and reliable income."
      ],
      "read": "This income strategy aims for approximately 1% per month, focusing on parking cash for yield. It prioritizes low drawdown and steady monthly distributions from income-focused ETFs. While aiming for reliable income, distributions are variable, and NAV can still fall in a selloff, meaning it's not a savings account."
    }
  }
}