{
  "aiTs": "7/13/2026, 7:01:28 AM (Gemini)",
  "aiEpoch": 1783940488171,
  "v": 10,
  "src": "Gemini",
  "modes": {
    "conservative": {
      "moves": [
        {
          "sym": "SPY",
          "action": "Trim",
          "targetPct": 20,
          "note": "Reduce concentration, meet mandate"
        },
        {
          "sym": "SOXL",
          "action": "Sell",
          "targetPct": 0,
          "note": "Cut all leveraged ETFs"
        },
        {
          "sym": "SPAL",
          "action": "Sell",
          "targetPct": 0,
          "note": "Cut all leveraged ETFs"
        },
        {
          "sym": "QQQI",
          "action": "Add",
          "targetPct": 25,
          "note": "Increase income, broad exposure"
        },
        {
          "sym": "CRWD",
          "action": "Trim",
          "targetPct": 10,
          "note": "Reduce single name concentration"
        },
        {
          "sym": "TSLA",
          "action": "Watch",
          "targetPct": 5,
          "note": "High-quality, strong scanner setup"
        }
      ],
      "plan": [
        "Trim SPY to 20% to reduce concentration and meet the mandate.",
        "Sell all SOXL and SPAL to eliminate leveraged ETF exposure for capital preservation.",
        "Increase QQQI to 25% for more income and broad market exposure.",
        "Trim CRWD to 10% to reduce single name concentration.",
        "Hold 15% cash buffer for stability.",
        "Watch TSLA for a potential small 5% buy if it triggers."
      ],
      "read": "This conservative plan aims for approximately 1.5% monthly return, prioritizing capital preservation. Risk is significantly reduced by cutting leveraged ETFs and limiting concentration, leading to lower expected drawdowns."
    },
    "balanced": {
      "moves": [
        {
          "sym": "SPY",
          "action": "Trim",
          "targetPct": 25,
          "note": "Reduce concentration, meet mandate"
        },
        {
          "sym": "SOXL",
          "action": "Sell",
          "targetPct": 0,
          "note": "Exit flagged leveraged ETF"
        },
        {
          "sym": "SPAL",
          "action": "Trim",
          "targetPct": 2,
          "note": "Reduce leveraged ETF exposure"
        },
        {
          "sym": "CRWD",
          "action": "Add",
          "targetPct": 15,
          "note": "Add to strong AI/Software name"
        },
        {
          "sym": "TSLA",
          "action": "Buy",
          "targetPct": 5,
          "note": "Add high-quality growth setup"
        },
        {
          "sym": "QQQI",
          "action": "Add",
          "targetPct": 22,
          "note": "Slightly increase income exposure"
        }
      ],
      "plan": [
        "Trim SPY to 25% to meet the concentration mandate.",
        "Sell SOXL completely as it is flagged for exit.",
        "Reduce SPAL to 2% to lower leveraged ETF exposure.",
        "Add to CRWD, a strong AI/Software name, to 15%.",
        "Buy TSLA for 5% of the book, a high-quality growth setup.",
        "Increase QQQI to 22% for balanced income and broad exposure."
      ],
      "read": "This balanced plan targets around 2.5% monthly return, focusing on risk-first growth. Leverage is reduced, and concentration is managed, aiming for a moderate risk profile with controlled drawdowns."
    },
    "aggressive": {
      "moves": [
        {
          "sym": "SPY",
          "action": "Trim",
          "targetPct": 25,
          "note": "Reduce concentration, meet mandate"
        },
        {
          "sym": "SOXL",
          "action": "Sell",
          "targetPct": 0,
          "note": "Exit flagged leveraged ETF"
        },
        {
          "sym": "SPAL",
          "action": "Add",
          "targetPct": 5,
          "note": "Increase leveraged ETF exposure"
        },
        {
          "sym": "CRWD",
          "action": "Add",
          "targetPct": 20,
          "note": "Concentrate in strong AI/Software"
        },
        {
          "sym": "TSLA",
          "action": "Buy",
          "targetPct": 10,
          "note": "High-scoring growth setup"
        },
        {
          "sym": "NVDU",
          "action": "Buy",
          "targetPct": 5,
          "note": "Strong scanner setup, tech focus"
        }
      ],
      "plan": [
        "Trim SPY to 25% to meet the concentration mandate.",
        "Sell SOXL completely as it is flagged for exit.",
        "Increase SPAL to 5% for leveraged exposure, staying within limits.",
        "Add to CRWD, concentrating in this strong AI/Software name to 20%.",
        "Buy TSLA for 10% of the book, a high-scoring growth setup.",
        "Buy NVDU for 5%, another strong scanner setup for tech exposure."
      ],
      "read": "This aggressive plan aims for approximately 4% monthly return, pursuing stretched growth. It involves higher leverage and concentration, increasing both potential upside and significant drawdown risk. Leveraged ETFs like SPAL are subject to decay and rebalancing, amplifying daily moves."
    },
    "income": {
      "moves": [
        {
          "sym": "SPY",
          "action": "Trim",
          "targetPct": 20,
          "note": "Reduce concentration, meet mandate"
        },
        {
          "sym": "SOXL",
          "action": "Sell",
          "targetPct": 0,
          "note": "Cut all leveraged ETFs"
        },
        {
          "sym": "SPAL",
          "action": "Sell",
          "targetPct": 0,
          "note": "Cut all leveraged ETFs"
        },
        {
          "sym": "QQQI",
          "action": "Add",
          "targetPct": 40,
          "note": "Maximize income-generating ETF"
        },
        {
          "sym": "QQQ",
          "action": "Trim",
          "targetPct": 10,
          "note": "Reduce broad index for income"
        },
        {
          "sym": "CRWD",
          "action": "Trim",
          "targetPct": 5,
          "note": "Reduce high-beta single name"
        }
      ],
      "plan": [
        "Trim SPY to 20% to reduce concentration and meet the mandate.",
        "Sell all SOXL and SPAL to eliminate leveraged ETF exposure.",
        "Increase QQQI to 40% to maximize income-generating exposure.",
        "Reduce QQQ to 10% to shift towards income focus.",
        "Trim CRWD to 5% to reduce high-beta single name exposure.",
        "Hold a 15% cash buffer for stability and potential distributions."
      ],
      "read": "This income plan targets around 1% monthly return, prioritizing steady distributions. It focuses on income and broad index ETFs, with minimal exposure to high-beta single names and no leveraged ETFs. While aiming for low drawdown, distributions are variable, and NAV can still decline in market selloffs."
    }
  }
}