[
  {
    "ts": "7/15/2026, 10:01:10 AM",
    "epoch": 1784124070094,
    "headline": "IRS chief Frank Bisignano will lead Trump Accounts expansion",
    "detail": "",
    "signal": "",
    "rec": ""
  },
  {
    "ts": "7/15/2026, 10:01:10 AM",
    "epoch": 1784124070094,
    "headline": "Warren Buffett on the market today: 'It's tough to find values when everybody is preferring gambling'",
    "detail": "",
    "signal": "",
    "rec": ""
  },
  {
    "ts": "7/15/2026, 10:01:10 AM",
    "epoch": 1784124070094,
    "headline": "Watch Fed Chairman Kevin Warsh testify live before Senate banking committee",
    "detail": "",
    "signal": "",
    "rec": ""
  },
  {
    "ts": "7/15/2026, 10:01:10 AM",
    "epoch": 1784124070094,
    "headline": "‘Arsenal of democracy’: Jamie Dimon announces $24 million effort to boost American shipbuilding",
    "detail": "",
    "signal": "",
    "rec": ""
  }
]