[
  {
    "ts": "7/17/2026, 6:46:01 PM",
    "epoch": 1784328361124,
    "headline": "Meet Kimi K3, the newest Chinese AI model haunting Silicon Valley",
    "detail": "",
    "signal": "",
    "rec": ""
  },
  {
    "ts": "7/17/2026, 6:46:01 PM",
    "epoch": 1784328361124,
    "headline": "Taco Bell says it has removed lettuce linked to cyclosporiasis outbreak from its restaurants",
    "detail": "",
    "signal": "",
    "rec": ""
  },
  {
    "ts": "7/17/2026, 6:46:01 PM",
    "epoch": 1784328361124,
    "headline": "The average stock is having a moment as semiconductors struggle. It&#x2019;s a sign of a healthy market.",
    "detail": "",
    "signal": "",
    "rec": ""
  },
  {
    "ts": "7/17/2026, 6:46:01 PM",
    "epoch": 1784328361124,
    "headline": "19 (mostly) tech stocks that have fallen at least 25% in July",
    "detail": "",
    "signal": "",
    "rec": ""
  }
]