[
  {
    "ts": "7/10/2026, 4:31:03 PM",
    "epoch": 1783715463997,
    "headline": "How Apple stock rode the AI rollercoaster to record highs in 1 chart",
    "detail": "",
    "signal": "",
    "rec": ""
  },
  {
    "ts": "7/10/2026, 4:31:03 PM",
    "epoch": 1783715463997,
    "headline": "SK Hynix rises 13% in Nasdaq debut. Chairman tells CNBC 'demand is enormous'",
    "detail": "",
    "signal": "",
    "rec": ""
  },
  {
    "ts": "7/10/2026, 4:31:03 PM",
    "epoch": 1783715463997,
    "headline": "Meta's stock has best week since early 2024 as optimism builds around AI strategy",
    "detail": "",
    "signal": "",
    "rec": ""
  },
  {
    "ts": "7/10/2026, 4:31:03 PM",
    "epoch": 1783715463997,
    "headline": "Stablecoin issuer Circle just got the greenlight to operate as a bank. The shares are up 5%",
    "detail": "",
    "signal": "",
    "rec": ""
  }
]